cars/__init__.py
cars/admin.py
cars/apps.py
cars/car_data.py
cars/models.py
cars/tests.py
cars/views.py
cars/management/commands/__init__.py
cars/management/commands/load_car_data.py
cars/management/commands/__pycache__/__init__.cpython-312.pyc
cars/management/commands/__pycache__/load_car_data.cpython-312.pyc
cars/migrations/__init__.py
cars/migrations/__pycache__/__init__.cpython-312.pyc
django_cars/__init__.py
django_cars/settings.py
django_cars/urls.py
django_cars/wsgi.py
django_cars-0.2.dist-info/LICENSE
django_cars-0.2.dist-info/METADATA
django_cars-0.2.dist-info/WHEEL
django_cars-0.2.dist-info/top_level.txt
django_cars-0.2.dist-info/RECORD
