Metadata-Version: 2.1
Name: django_cars
Version: 0.2
Summary: A Django app for managing car data
Home-page: https://github.com/jafar-sadigzade/django_cars
Author: Jafar Sadigzade
Author-email: jafarsadigzade@gmail.com
License: MIT License
Classifier: Environment :: Web Environment
Classifier: Framework :: Django
Classifier: Framework :: Django :: 5.0
Classifier: Intended Audience :: Developers
Classifier: License :: OSI Approved :: MIT License
Classifier: Operating System :: OS Independent
Classifier: Programming Language :: Python
Classifier: Programming Language :: Python :: 3.12
Classifier: Topic :: Internet :: WWW/HTTP
Classifier: Topic :: Internet :: WWW/HTTP :: Dynamic Content
License-File: LICENSE
Requires-Dist: Django >=5.0
